quick_time/__init__.py
quick_time/time.py
quick_time-1.1.dist-info/METADATA
quick_time-1.1.dist-info/WHEEL
quick_time-1.1.dist-info/top_level.txt
quick_time-1.1.dist-info/RECORD
