Metadata-Version: 2.1
Name: quick-time
Version: 1.1
Summary: quick time
Home-page: https://github.com/keegang6705/instant-time
Author: keegang_6705
Author-email: darunphobwi@gmail.com
License: MIT
Platform: UNKNOWN
Requires-Python: >=3.0
Requires-Dist: datetime
Requires-Dist: pytz
